livechat_scraper/builders/__init__.py
livechat_scraper/builders/continuation_fetcher.py
livechat_scraper/builders/message_factory.py
livechat_scraper/builders/player_state.py
livechat_scraper/constants/__init__.py
livechat_scraper/constants/node_constants.py
livechat_scraper/constants/scraper_constants.py
livechat_scraper/extractors/__init__.py
livechat_scraper/extractors/initial_document_extractor.py
livechat_scraper/generators/__init__.py
livechat_scraper/generators/output_generator.py
livechat_scraper/messages/__init__.py
livechat_scraper/messages/chat_message.py
livechat_scraper/messages/membership_gifted_message.py
livechat_scraper/messages/membership_message.py
livechat_scraper/messages/membership_redeemed_message.py
livechat_scraper/messages/message.py
livechat_scraper/messages/pinned_message.py
livechat_scraper/messages/placeholderItem_message.py
livechat_scraper/messages/purchased_sticker_message.py
livechat_scraper/messages/superchat_message.py
livechat_scraper/messages/fragments/__init__.py
livechat_scraper/messages/fragments/content.py
livechat_scraper/messages/fragments/emoji.py
livechat_scraper/parsers/__init__.py
livechat_scraper/parsers/livechat_parser.py
livechat_scraper/requestors/__init__.py
livechat_scraper/requestors/continuation_requestor.py
livechat_scraper/requestors/initial_document_requestor.py
livechat_scraper/requestors/livechat_requestor.py
livechat_scraper/requestors/requestor.py
livechat_scraper/requestors/subsequent_requestor.py
livechat_scraper/scrapers/__init__.py
livechat_scraper/scrapers/livechat_scraper.py
livechat_scraper/scrapers/scraper_initializer.py
livechat_scraper/scrapers/video.py
youtube_livechat_scraper_ohn0-1.0.5.dist-info/METADATA
youtube_livechat_scraper_ohn0-1.0.5.dist-info/WHEEL
youtube_livechat_scraper_ohn0-1.0.5.dist-info/licenses/LICENSE
youtube_livechat_scraper_ohn0-1.0.5.dist-info/RECORD
