Metadata-Version: 2.1
Name: youtube-livechat-scraper-ohn0
Version: 1.0.5
Summary: Livechat scraper for Youtube video streams
Project-URL: Homepage, https://github.com/ohn0/youtube-livechat-scraper
Author-email: ohn0 <silverskinx@gmail.com>
License-File: LICENSE
Classifier: License :: OSI Approved :: MIT License
Classifier: Operating System :: OS Independent
Classifier: Programming Language :: Python :: 3
Requires-Python: >=3.10
Requires-Dist: beautifulsoup4>=4.12.2
Requires-Dist: requests
